caqtus/__about__.py
caqtus/__init__.py
caqtus/formatter.py
caqtus/py.typed
caqtus/analysis/__init__.py
caqtus/analysis/loading/__init__.py
caqtus/analysis/loading/_combinable_importers.py
caqtus/analysis/loading/_load_image_count.py
caqtus/analysis/loading/_load_parameters.py
caqtus/analysis/loading/_load_shot_id.py
caqtus/analysis/loading/_load_shot_info.py
caqtus/analysis/loading/_shot_data.py
caqtus/analysis/stats/__init__.py
caqtus/analysis/stats/stats.py
caqtus/analysis/units/__init__.py
caqtus/analysis/units/units.py
caqtus/device/__init__.py
caqtus/device/_controller.py
caqtus/device/_name.py
caqtus/device/camera/__init__.py
caqtus/device/camera/_compiler.py
caqtus/device/camera/_configuration.py
caqtus/device/camera/_controller.py
caqtus/device/camera/_proxy.py
caqtus/device/camera/_runtime.py
caqtus/device/configuration/__init__.py
caqtus/device/configuration/_configuration.py
caqtus/device/configuration/_converter.py
caqtus/device/configuration/_parameter.py
caqtus/device/configuration/serializer/__init__.py
caqtus/device/configuration/serializer/_implementation.py
caqtus/device/configuration/serializer/_protocol.py
caqtus/device/output_transform/__init__.py
caqtus/device/output_transform/_converter.py
caqtus/device/output_transform/_output_mapping.py
caqtus/device/output_transform/_transformation.py
caqtus/device/remote/__init__.py
caqtus/device/remote/_async_converter.py
caqtus/device/remote/_device_proxy.py
caqtus/device/remote/_proxy.py
caqtus/device/remote/rpc/__init__.py
caqtus/device/remote/rpc/_client.py
caqtus/device/remote/rpc/_configuration.py
caqtus/device/remote/rpc/_prefix_size.py
caqtus/device/remote/rpc/_server.py
caqtus/device/runtime/__init__.py
caqtus/device/runtime/_device.py
caqtus/device/runtime/_installed_devices_discovery.py
caqtus/device/runtime/runtime_device.py
caqtus/device/sequencer/__init__.py
caqtus/device/sequencer/_controller.py
caqtus/device/sequencer/_converter.py
caqtus/device/sequencer/_proxy.py
caqtus_suite-6.28.0.dist-info/METADATA
caqtus_suite-6.28.0.dist-info/WHEEL
caqtus_suite-6.28.0.dist-info/licenses/license.md
caqtus_suite-6.28.0.dist-info/RECORD
