Metadata-Version: 2.4
Name: caqtus-suite
Version: 6.28.0
Summary: Package to control a cold atom experiment
Project-URL: Documentation, https://caqtus.readthedocs.io/en/stable/
Project-URL: Issues, https://github.com/light-scattering-io/caqtus/issues
Project-URL: Source, https://github.com/light-scattering-io/caqtus
Author-email: light-scattering-io <lecaqtus66@gmail.com>
License: Copyright 2024 Université Paris-Saclay
License-File: license.md
Classifier: Development Status :: 4 - Beta
Classifier: Intended Audience :: Science/Research
Classifier: Programming Language :: Python
Classifier: Programming Language :: Python :: 3.12
Classifier: Programming Language :: Python :: 3.13
Classifier: Programming Language :: Python :: Implementation :: CPython
Classifier: Topic :: Scientific/Engineering
Classifier: Topic :: Scientific/Engineering :: Physics
Requires-Python: >=3.12
Requires-Dist: aiosqlite>=0.20.0
Requires-Dist: alembic>=1.13
Requires-Dist: anyio[trio]>=4.3.0
Requires-Dist: attrs>=23.2.0
Requires-Dist: caqtus-parsing>=0.4.0
Requires-Dist: cattrs>=24.1.1
Requires-Dist: eliot>=1.15.0
Requires-Dist: graphviz>=0.20.3
Requires-Dist: matplotlib>=3.8.3
Requires-Dist: multipledispatch>=1.0.0
Requires-Dist: numpy>=2.0
Requires-Dist: pint>=0.24
Requires-Dist: polars>=1.25.1
Requires-Dist: psycopg[binary]>=3.1.18
Requires-Dist: pyqtgraph>=0.13.4
Requires-Dist: pyside6>=6.8.2
Requires-Dist: python-benedict>=0.33.2
Requires-Dist: pyyaml>=6.0.1
Requires-Dist: qtawesome>=1.3.0
Requires-Dist: scipy>=1.12.0
Requires-Dist: setuptools
Requires-Dist: sqlalchemy-utils>=0.41.1
Requires-Dist: sqlalchemy>=2.0.28
Requires-Dist: sympy>=1.12
Requires-Dist: tblib>=3.0.0
Requires-Dist: token-utils>=0.1.8
Requires-Dist: tqdm>=4.66.5
Requires-Dist: typing-extensions>=4.10.0
